<?xml version="1.0" encoding="utf-8" ?>
<!-- Don`t EDIT this FILE! -->
<content>
 
  <!-- -=== VECTOR MASTER ===- -->

  <!-- Vector Master Phrases -->
  <phrase id="VectorMaster.Word.Name">Ім'я</phrase>
  <phrase id="VectorMaster.Word.Resolution">Розд. здатність</phrase>
  <phrase id="VectorMaster.Word.Bytes">Байт</phrase>
  <phrase id="VectorMaster.Word.KBytes">КБ</phrase>
  <phrase id="VectorMaster.Word.MBytes">МБ</phrase>
  <phrase id="VectorMaster.Word.Size">Розміри</phrase>
  <phrase id="VectorMaster.Word.Dpi">DPI</phrase>
  <phrase id="VectorMaster.Word.PixelFormat">Формат пікс.</phrase>
  <phrase id="VectorMaster.Word.TimeSpend">Пройшло часу:</phrase>
  <phrase id="VectorMaster.Word.Complete">Завершено!</phrase>
  <phrase id="VectorMaster.Word.Update">Оновити</phrase>
  <phrase id="VectorMaster.Word.Scale">Розмір</phrase>
  <phrase id="VectorMaster.Word.Stop">Стоп</phrase>
  <phrase id="VectorMaster.Word.Threshold">Поріг</phrase>
  <phrase id="VectorMaster.Word.Sigma">Сигма</phrase>
  <phrase id="VectorMaster.CantCalculateDPI">Неможливо підрахувати.</phrase>
  <phrase id="VectorMaster.AllImageFiles">Усі формати зображень</phrase>
  <phrase id="VectorMaster.AllFiles">Усі файли</phrase>

  <!-- Vector Master Menus -->
  <menu id="Form_VectorMaster.label_colormod">Колір. модель:</menu>
  <menu id="Form_VectorMaster.label_1">Вітання    </menu>
  <menu id="Form_VectorMaster.label_2">  Вибір файлу</menu>
  <menu id="Form_VectorMaster.label_3">     Первинна &#009;&#xA;     обробка  </menu>
  <menu id="Form_VectorMaster.label_4">     Чорно-білий &#009;&#xA;     формат</menu>
  <menu id="Form_VectorMaster.label_5">    Детектор граней</menu>
  <menu id="Form_VectorMaster.label_6"> Підготовка</menu>
  <menu id="Form_VectorMaster.label_7">     Векторизація   </menu>
  <menu id="Form_VectorMaster.label_gauss_scale">Розмір:  7</menu>
  <menu id="Form_VectorMaster.label_gauss_sigma">Сигма: 1.2</menu>
  <menu id="Form_VectorMaster.label_harbw">Поріг: 128</menu>
  <menu id="Form_VectorMaster.label_imgname">Ім'я: </menu>
  <menu id="Form_VectorMaster.label_instr">Слідуйте інтрукціям...&#009;&#xA;</menu>
  <menu id="Form_VectorMaster.label_path">Зображення: not set</menu>
  <menu id="Form_VectorMaster.label_percentage">--</menu>
  <menu id="Form_VectorMaster.label_resolution">Розд. здатність: not set</menu>
  <menu id="Form_VectorMaster.label_resolution_">Розд. здатність: </menu>
  <menu id="Form_VectorMaster.label_size">Розмір: not set</menu>
  <menu id="Form_VectorMaster.label_sobel">Поріг: 125</menu>
  <menu id="Form_VectorMaster.label_strcount">Кол-во потоків:</menu>
  <menu id="Form_VectorMaster.label_timespend">Time:</menu>
  <menu id="Form_VectorMaster.label_title">Векторизація&#009;&#xA;растра</menu>
  <menu id="Form_VectorMaster.label_titlle1">Вас вітає майтсе векторизації зображень&#009;&#xA;</menu>
  <menu id="Form_VectorMaster.button_back_img">Назад</menu>
  <menu id="Form_VectorMaster.button_back_pr">Назад</menu>
  <menu id="Form_VectorMaster.button_back_tab2">Назад</menu>
  <menu id="Form_VectorMaster.button_back_tab3">Назад</menu>
  <menu id="Form_VectorMaster.button_back_tab4">Назад</menu>
  <menu id="Form_VectorMaster.button_exit">Вийти</menu>
  <menu id="Form_VectorMaster.button_exit_tab0">Назад</menu>
  <menu id="Form_VectorMaster.button_help">Поміч</menu>
  <menu id="Form_VectorMaster.button_loadimage">Відкрити</menu>
  <menu id="Form_VectorMaster.button_next">Далі</menu>
  <menu id="Form_VectorMaster.button_next1">Далі</menu>
  <menu id="Form_VectorMaster.button_next_tab0">Далі</menu>
  <menu id="Form_VectorMaster.button_next_tab2">Далі</menu>
  <menu id="Form_VectorMaster.button_next_tab3">Далі</menu>
  <menu id="Form_VectorMaster.button_next_tab4">Вийти</menu>
  <menu id="Form_VectorMaster.button_openfolder">Відкрити теку</menu>
  <menu id="Form_VectorMaster.button_peview">+</menu>
  <menu id="Form_VectorMaster.button_pr">Векторизувати</menu>
  <menu id="Form_VectorMaster.button_print">На друк</menu>
  <menu id="Form_VectorMaster.button_remove">Видалити</menu>
  <menu id="Form_VectorMaster.button_savepr">Зберегти</menu>
  <menu id="Form_VectorMaster.button_show">Показати</menu>
  <menu id="Form_VectorMaster.button_update">Оновити</menu>
  <menu id="Form_VectorMaster.button_update_tab2">Оновити</menu>
  <menu id="Form_VectorMaster.button_update_tab3">Оновити</menu>
  <menu id="Form_VectorMaster.checkBox_useflip">Викор.&#009;&#xA;</menu>
  <menu id="Form_VectorMaster.groupBox_colormod">2х колірний формат</menu>
  <menu id="Form_VectorMaster.groupBox_flip">Відображення</menu>
  <menu id="Form_VectorMaster.groupBox_gauss">Розмиття по Гаусу</menu>
  <menu id="Form_VectorMaster.groupBox_grayform">Відтінки сірого</menu>
  <menu id="Form_VectorMaster.groupBox_rotate">Поворот</menu>
  <menu id="Form_VectorMaster.groupBox_sobel">Оператор Собеля</menu>
  <menu id="Form_VectorMaster.radioButton_0deg">0</menu>
  <menu id="Form_VectorMaster.radioButton_180deg">180</menu>
  <menu id="Form_VectorMaster.radioButton_270deg">270</menu>
  <menu id="Form_VectorMaster.radioButton_90deg">90</menu>
  <menu id="Form_VectorMaster.radioButton_flipx">По осі Х</menu>
  <menu id="Form_VectorMaster.radioButton_flipy">По осі Y</menu>
  <menu id="Form_VectorMaster.radioButton_grayform">Відтінки сірого</menu>
  <menu id="Form_VectorMaster.radioButton_hardbw">2х колірний формат</menu>

</content>
